giphy_compose_testing_v0_sdk/__init__.py
giphy_compose_testing_v0_sdk/api_client.py
giphy_compose_testing_v0_sdk/api_response.py
giphy_compose_testing_v0_sdk/configuration.py
giphy_compose_testing_v0_sdk/exceptions.py
giphy_compose_testing_v0_sdk/py.typed
giphy_compose_testing_v0_sdk/rest.py
giphy_compose_testing_v0_sdk/api/__init__.py
giphy_compose_testing_v0_sdk/api/gifs_api.py
giphy_compose_testing_v0_sdk/api/stickers_api.py
giphy_compose_testing_v0_sdk/models/__init__.py
giphy_compose_testing_v0_sdk/models/get_gifs_by_id200_response.py
giphy_compose_testing_v0_sdk/models/gif.py
giphy_compose_testing_v0_sdk/models/gif_images.py
giphy_compose_testing_v0_sdk/models/gif_images_downsized.py
giphy_compose_testing_v0_sdk/models/gif_images_downsized_large.py
giphy_compose_testing_v0_sdk/models/gif_images_downsized_medium.py
giphy_compose_testing_v0_sdk/models/gif_images_downsized_small.py
giphy_compose_testing_v0_sdk/models/gif_images_downsized_still.py
giphy_compose_testing_v0_sdk/models/gif_images_fixed_height.py
giphy_compose_testing_v0_sdk/models/gif_images_fixed_height_downsampled.py
giphy_compose_testing_v0_sdk/models/gif_images_fixed_height_small.py
giphy_compose_testing_v0_sdk/models/gif_images_fixed_height_small_still.py
giphy_compose_testing_v0_sdk/models/gif_images_fixed_height_still.py
giphy_compose_testing_v0_sdk/models/gif_images_fixed_width.py
giphy_compose_testing_v0_sdk/models/gif_images_fixed_width_downsampled.py
giphy_compose_testing_v0_sdk/models/gif_images_fixed_width_small.py
giphy_compose_testing_v0_sdk/models/gif_images_fixed_width_small_still.py
giphy_compose_testing_v0_sdk/models/gif_images_fixed_width_still.py
giphy_compose_testing_v0_sdk/models/gif_images_looping.py
giphy_compose_testing_v0_sdk/models/gif_images_original.py
giphy_compose_testing_v0_sdk/models/gif_images_original_still.py
giphy_compose_testing_v0_sdk/models/gif_images_preview.py
giphy_compose_testing_v0_sdk/models/gif_images_preview_gif.py
giphy_compose_testing_v0_sdk-1.0.0.dist-info/METADATA
giphy_compose_testing_v0_sdk-1.0.0.dist-info/WHEEL
giphy_compose_testing_v0_sdk-1.0.0.dist-info/top_level.txt
giphy_compose_testing_v0_sdk-1.0.0.dist-info/RECORD
